examples/__init__.py
examples/encrypt_decrypt_large_file.py
examples/publish_card_from_client_side.py
examples/sample_backend_for_jwt_generation.py
examples/search_card_on_client_side.py
virgil_sdk/__init__.py
virgil_sdk/cards/__init__.py
virgil_sdk/cards/card.py
virgil_sdk/cards/card_manager.py
virgil_sdk/cards/card_signature.py
virgil_sdk/cards/raw_card_content.py
virgil_sdk/client/__init__.py
virgil_sdk/client/base_card_client.py
virgil_sdk/client/card_client.py
virgil_sdk/client/client_exception.py
virgil_sdk/client/expired_authorization_client_exception.py
virgil_sdk/client/raw_signature.py
virgil_sdk/client/raw_signed_model.py
virgil_sdk/client/unauthorized_client_exception.py
virgil_sdk/client/connections/__init__.py
virgil_sdk/client/connections/base_connection.py
virgil_sdk/client/connections/base_request.py
virgil_sdk/client/connections/http_request_adapter.py
virgil_sdk/client/connections/request.py
virgil_sdk/client/connections/service_connection.py
virgil_sdk/client/connections/service_error.py
virgil_sdk/client/connections/urllib.py
virgil_sdk/client/connections/virgil_agent_adapter.py
virgil_sdk/jwt/__init__.py
virgil_sdk/jwt/jwt.py
virgil_sdk/jwt/jwt_body_content.py
virgil_sdk/jwt/jwt_generator.py
virgil_sdk/jwt/jwt_header_content.py
virgil_sdk/jwt/jwt_verifier.py
virgil_sdk/jwt/token_context.py
virgil_sdk/jwt/abstractions/__init__.py
virgil_sdk/jwt/abstractions/access_token.py
virgil_sdk/jwt/abstractions/access_token_provider.py
virgil_sdk/jwt/providers/__init__.py
virgil_sdk/jwt/providers/caching_callback_provider.py
virgil_sdk/jwt/providers/callback_jwt_provider.py
virgil_sdk/jwt/providers/const_access_token_provider.py
virgil_sdk/jwt/providers/generator_jwt_provider.py
virgil_sdk/signers/__init__.py
virgil_sdk/signers/model_signer.py
virgil_sdk/storage/__init__.py
virgil_sdk/storage/key_entry.py
virgil_sdk/storage/key_storage.py
virgil_sdk/storage/private_key_exporter.py
virgil_sdk-5.3.0.dist-info/DESCRIPTION.rst
virgil_sdk-5.3.0.dist-info/METADATA
virgil_sdk-5.3.0.dist-info/RECORD
virgil_sdk-5.3.0.dist-info/WHEEL
virgil_sdk-5.3.0.dist-info/metadata.json
virgil_sdk-5.3.0.dist-info/top_level.txt
