Metadata-Version: 2.0
Name: virgil-sdk
Version: 5.3.0
Summary: 
Home-page: https://virgilsecurity.com/
Author: Virgil Security
Author-email: support@virgilsecurity.com
License: BSD
Platform: UNKNOWN
Classifier: Development Status :: 5 - Production/Stable
Classifier: License :: OSI Approved :: BSD License
Classifier: Natural Language :: English
Classifier: Programming Language :: Python :: 2.7
Classifier: Programming Language :: Python :: 3.4
Classifier: Programming Language :: Python :: 3.5
Classifier: Programming Language :: Python :: 3.6
Classifier: Programming Language :: Python :: 3.7
Classifier: Topic :: Security :: Cryptography
Requires-Dist: virgil-crypto (>=5.0.0)
